ethter/__init__.py
ethter/constants.py
ethter/exceptions.py
ethter/main.py
ethter/rpc.py
ethter/backends/__init__.py
ethter/backends/base.py
ethter/backends/common.py
ethter/backends/mock/__init__.py
ethter/backends/mock/common.py
ethter/backends/mock/factory.py
ethter/backends/mock/main.py
ethter/backends/mock/serializers.py
ethter/backends/pyevm/__init__.py
ethter/backends/pyevm/main.py
ethter/backends/pyevm/serializers.py
ethter/backends/pyevm/utils.py
ethter/normalization/__init__.py
ethter/normalization/base.py
ethter/normalization/common.py
ethter/normalization/default.py
ethter/normalization/inbound.py
ethter/normalization/outbound.py
ethter/tools/__init__.py
ethter/tools/gas_burner_contract.py
ethter/utils/__init__.py
ethter/utils/accounts.py
ethter/utils/address.py
ethter/utils/backend_testing.py
ethter/utils/based.py
ethter/utils/emitter_contract.py
ethter/utils/encoding.py
ethter/utils/filters.py
ethter/utils/math_contract.py
ethter/utils/module_loading.py
ethter/utils/throws_contract.py
ethter/utils/transactions.py
ethter/validation/__init__.py
ethter/validation/base.py
ethter/validation/common.py
ethter/validation/default.py
ethter/validation/inbound.py
ethter/validation/outbound.py
ethter-1.10.1b1.dist-info/LICENSE
ethter-1.10.1b1.dist-info/METADATA
ethter-1.10.1b1.dist-info/WHEEL
ethter-1.10.1b1.dist-info/top_level.txt
ethter-1.10.1b1.dist-info/RECORD
