Metadata-Version: 2.1
Name: ethter
Version: 1.10.1b1
Summary: Tools for testing Ethereum applications.
Home-page: https://github.com/ethtertesting/ethter
Author: Ethter testing
Author-email: ethtertesting@gmail.com
License: MIT
Keywords: ethereum
Classifier: Development Status :: 2 - Pre-Alpha
Classifier: Intended Audience :: Developers
Classifier: License :: OSI Approved :: MIT License
Classifier: Natural Language :: English
Classifier: Programming Language :: Python :: 3
Classifier: Programming Language :: Python :: 3.7
Classifier: Programming Language :: Python :: 3.8
Classifier: Programming Language :: Python :: 3.9
Classifier: Programming Language :: Python :: 3.10
Requires-Python: >=3.6.8,<4
License-File: LICENSE
Requires-Dist: eth-abi (>=3.0.1)
Requires-Dist: eth-account (>=0.6.0)
Requires-Dist: eth-keys (<0.5.0,>=0.4.0)
Requires-Dist: eth-utils (<3.0.0,>=2.0.0)
Requires-Dist: rlp (<4,>=3.0.0)
Requires-Dist: semantic-version (<3.0.0,>=2.6.0)
Provides-Extra: dev
Requires-Dist: bumpversion (<1.0.0,>=0.5.3) ; extra == 'dev'
Requires-Dist: tox (<3.0.0,>=2.9.1) ; extra == 'dev'
Requires-Dist: wheel (<1.0.0,>=0.30.0) ; extra == 'dev'
Requires-Dist: pytest (>=7.0.0) ; extra == 'dev'
Requires-Dist: pytest-xdist (<3,>=2.0.0) ; extra == 'dev'
Requires-Dist: eth-hash[pycryptodome] (<1.0.0,>=0.1.4) ; extra == 'dev'
Requires-Dist: py-evm (==0.7.0a4) ; extra == 'dev'
Requires-Dist: black (<23,>=22) ; extra == 'dev'
Requires-Dist: flake8 (<4.0.0,>=3.5.0) ; extra == 'dev'
Requires-Dist: towncrier (<22,>=21) ; extra == 'dev'
Requires-Dist: eth-hash[pysha3] (<1.0.0,>=0.1.4) ; (implementation_name == "cpython") and extra == 'dev'
Requires-Dist: eth-hash[pycryptodome] (<1.0.0,>=0.1.4) ; (implementation_name == "pypy") and extra == 'dev'
Provides-Extra: docs
Requires-Dist: towncrier (<22,>=21) ; extra == 'docs'
Provides-Extra: lint
Requires-Dist: black (<23,>=22) ; extra == 'lint'
Requires-Dist: flake8 (<4.0.0,>=3.5.0) ; extra == 'lint'
Provides-Extra: py-evm
Requires-Dist: py-evm (==0.7.0a4) ; extra == 'py-evm'
Requires-Dist: eth-hash[pysha3] (<1.0.0,>=0.1.4) ; (implementation_name == "cpython") and extra == 'py-evm'
Requires-Dist: eth-hash[pycryptodome] (<1.0.0,>=0.1.4) ; (implementation_name == "pypy") and extra == 'py-evm'
Provides-Extra: pyevm
Requires-Dist: py-evm (==0.7.0a4) ; extra == 'pyevm'
Requires-Dist: eth-hash[pysha3] (<1.0.0,>=0.1.4) ; (implementation_name == "cpython") and extra == 'pyevm'
Requires-Dist: eth-hash[pycryptodome] (<1.0.0,>=0.1.4) ; (implementation_name == "pypy") and extra == 'pyevm'
Provides-Extra: test
Requires-Dist: pytest (>=7.0.0) ; extra == 'test'
Requires-Dist: pytest-xdist (<3,>=2.0.0) ; extra == 'test'
Requires-Dist: eth-hash[pycryptodome] (<1.0.0,>=0.1.4) ; extra == 'test'
